Pavlov-0.1.3.dist-info/METADATA
Pavlov-0.1.3.dist-info/RECORD
Pavlov-0.1.3.dist-info/WHEEL
Pavlov-0.1.3.dist-info/top_level.txt
pavlov/__init__.py
pavlov/actors/__init__.py
pavlov/actors/actors.py
pavlov/agents/__init__.py
pavlov/agents/agents.py
pavlov/auxiliary/__init__.py
pavlov/auxiliary/monitor.py
pavlov/auxiliary/replay_buffer.py
pavlov/auxiliary/schedules.py
pavlov/models/__init__.py
pavlov/models/common.py
pavlov/models/ddpg.py
pavlov/models/dqn.py
pavlov/models/topology.py
pavlov/pipeline/__init__.py
pavlov/pipeline/pipeline.py
pavlov/pipeline/transformations.py
pavlov/util/__init__.py
pavlov/util/exceptions.py
