Metadata-Version: 2.1
Name: Pavlov
Version: 0.1.3
Summary: A modular reinforcement learning pipeline with Keras
Home-page: https://github.com/ntaylorwss/pavlov
Author: Nash Taylor
Author-email: nashtaylor22@gmail.com
License: MIT
Download-URL: https://github.com/ntaylorwss/pavlov/archive/master.zip
Platform: UNKNOWN
Classifier: Programming Language :: Python :: 3
Classifier: License :: OSI Approved :: MIT License
Classifier: Operating System :: OS Independent
